Metadata-Version: 1.0
Name: word2vec-SISG
Version: 1.0.0
Summary: <Billion-scale Recommendation with Heterogeneous Side Information at Taobao> PyTorch implementation
Home-page: UNKNOWN
Author: UNKNOWN
Author-email: UNKNOWN
License: UNKNOWN
Platform: UNKNOWN
